MANIFEST.in
README.md
setup.py
save_ipython_variables/__init__.py
save_ipython_variables/save_variables.py
save_ipython_variables.egg-info/PKG-INFO
save_ipython_variables.egg-info/SOURCES.txt
save_ipython_variables.egg-info/dependency_links.txt
save_ipython_variables.egg-info/top_level.txt