Metadata-Version: 1.0
Name: save-ipython-variables
Version: 0.0.3
Summary: A tool for saving your IPython variables to disk.
Home-page: https://github.com/sergeio/save_ipython_variables
Author: Sergei Orlov
Author-email: pypi@sergeiorlov.com
License: BSD
Platform: UNKNOWN
Classifier: Development Status :: 2 - Pre-Alpha
Classifier: Intended Audience :: Developers
Classifier: License :: OSI Approved :: BSD License
Classifier: Operating System :: MacOS :: MacOS X
Classifier: Operating System :: POSIX
Classifier: Programming Language :: Python
